CAlearn/__init__.py
CAlearn/_program.py
CAlearn/fitness.py
CAlearn/functions.py
CAlearn/genetic.py
CAlearn/utils.py
CAlearn-0.0.3.dist-info/LICENSE
CAlearn-0.0.3.dist-info/METADATA
CAlearn-0.0.3.dist-info/WHEEL
CAlearn-0.0.3.dist-info/top_level.txt
CAlearn-0.0.3.dist-info/RECORD
