Metadata-Version: 2.1
Name: CAlearn
Version: 0.0.3
Summary: Genetic Programming in Python, with a scikit-learn inspired API. Generating corresponding rule formula from given Cellular Automaton.
Home-page: https://github.com/ChenShuMath/CAlearn
Author: Chen Shu
Author-email: shuchen.math@gmail.com
License: new BSD
Platform: UNKNOWN
Classifier: Development Status :: 3 - Alpha
Classifier: Intended Audience :: Science/Research
Classifier: Intended Audience :: Developers
Classifier: License :: OSI Approved
Classifier: Topic :: Software Development
Classifier: Topic :: Scientific/Engineering
Classifier: Operating System :: Microsoft :: Windows
Classifier: Operating System :: Unix
Classifier: Operating System :: MacOS
Classifier: Programming Language :: Python
Classifier: Programming Language :: Python :: 3
Classifier: Programming Language :: Python :: 3.5
Classifier: Programming Language :: Python :: 3.6
Classifier: Programming Language :: Python :: 3.7
Classifier: Programming Language :: Python :: 3.8
License-File: LICENSE
Requires-Dist: scikit-learn (>=0.22.1)
Requires-Dist: joblib (>=0.13.0)
